{"nodes": [{"id": "home_user_arcium_messenger_arcium_psi_programs_arcium_psi_src_lib_rs", "label": "lib.rs", "file_type": "code", "source_file": "arcium-psi/programs/arcium-psi/src/lib.rs", "source_location": "L1"}, {"id": "src_lib_init_user", "label": "init_user()", "file_type": "code", "source_file": "arcium-psi/programs/arcium-psi/src/lib.rs", "source_location": "L11"}, {"id": "context", "label": "Context", "file_type": "code", "source_file": "arcium-psi/programs/arcium-psi/src/lib.rs", "source_location": "L11"}, {"id": "inituser", "label": "InitUser", "file_type": "code", "source_file": "arcium-psi/programs/arcium-psi/src/lib.rs", "source_location": "L11"}, {"id": "result", "label": "Result", "file_type": "code", "source_file": "arcium-psi/programs/arcium-psi/src/lib.rs", "source_location": "L11"}, {"id": "src_lib_submit_query", "label": "submit_query()", "file_type": "code", "source_file": "arcium-psi/programs/arcium-psi/src/lib.rs", "source_location": "L19"}, {"id": "submitquery", "label": "SubmitQuery", "file_type": "code", "source_file": "arcium-psi/programs/arcium-psi/src/lib.rs", "source_location": "L19"}, {"id": "vec", "label": "Vec", "file_type": "code", "source_file": "arcium-psi/programs/arcium-psi/src/lib.rs", "source_location": "L19"}, {"id": "src_lib_init_psi_intersect_comp_def", "label": "init_psi_intersect_comp_def()", "file_type": "code", "source_file": "arcium-psi/programs/arcium-psi/src/lib.rs", "source_location": "L37"}, {"id": "initpsiintersectcompdef", "label": "InitPsiIntersectCompDef", "file_type": "code", "source_file": "arcium-psi/programs/arcium-psi/src/lib.rs", "source_location": "L37"}, {"id": "src_lib_submit_psi_query", "label": "submit_psi_query()", "file_type": "code", "source_file": "arcium-psi/programs/arcium-psi/src/lib.rs", "source_location": "L52"}, {"id": "submitpsiquery", "label": "SubmitPsiQuery", "file_type": "code", "source_file": "arcium-psi/programs/arcium-psi/src/lib.rs", "source_location": "L52"}, {"id": "sharedencryptedstruct", "label": "SharedEncryptedStruct", "file_type": "code", "source_file": "arcium-psi/programs/arcium-psi/src/lib.rs", "source_location": "L52"}, {"id": "src_lib_psi_intersect_callback", "label": "psi_intersect_callback()", "file_type": "code", "source_file": "arcium-psi/programs/arcium-psi/src/lib.rs", "source_location": "L123"}, {"id": "psiintersectcallback", "label": "PsiIntersectCallback", "file_type": "code", "source_file": "arcium-psi/programs/arcium-psi/src/lib.rs", "source_location": "L123"}, {"id": "signedcomputationoutputs", "label": "SignedComputationOutputs", "file_type": "code", "source_file": "arcium-psi/programs/arcium-psi/src/lib.rs", "source_location": "L123"}, {"id": "psiintersectoutput", "label": "PsiIntersectOutput", "file_type": "code", "source_file": "arcium-psi/programs/arcium-psi/src/lib.rs", "source_location": "L123"}, {"id": "src_lib_inituser", "label": "InitUser", "file_type": "code", "source_file": "arcium-psi/programs/arcium-psi/src/lib.rs", "source_location": "L148"}, {"id": "account", "label": "Account", "file_type": "code", "source_file": "arcium-psi/programs/arcium-psi/src/lib.rs", "source_location": "L155"}, {"id": "userstate", "label": "UserState", "file_type": "code", "source_file": "arcium-psi/programs/arcium-psi/src/lib.rs", "source_location": "L155"}, {"id": "signer", "label": "Signer", "file_type": "code", "source_file": "arcium-psi/programs/arcium-psi/src/lib.rs", "source_location": "L157"}, {"id": "program", "label": "Program", "file_type": "code", "source_file": "arcium-psi/programs/arcium-psi/src/lib.rs", "source_location": "L158"}, {"id": "system", "label": "System", "file_type": "code", "source_file": "arcium-psi/programs/arcium-psi/src/lib.rs", "source_location": "L158"}, {"id": "src_lib_submitquery", "label": "SubmitQuery", "file_type": "code", "source_file": "arcium-psi/programs/arcium-psi/src/lib.rs", "source_location": "L162"}, {"id": "src_lib_initpsiintersectcompdef", "label": "InitPsiIntersectCompDef", "file_type": "code", "source_file": "arcium-psi/programs/arcium-psi/src/lib.rs", "source_location": "L174"}, {"id": "mxeaccount", "label": "MXEAccount", "file_type": "code", "source_file": "arcium-psi/programs/arcium-psi/src/lib.rs", "source_location": "L178"}, {"id": "uncheckedaccount", "label": "UncheckedAccount", "file_type": "code", "source_file": "arcium-psi/programs/arcium-psi/src/lib.rs", "source_location": "L181"}, {"id": "arcium", "label": "Arcium", "file_type": "code", "source_file": "arcium-psi/programs/arcium-psi/src/lib.rs", "source_location": "L188"}, {"id": "src_lib_submitpsiquery", "label": "SubmitPsiQuery", "file_type": "code", "source_file": "arcium-psi/programs/arcium-psi/src/lib.rs", "source_location": "L194"}, {"id": "arciumsigneraccount", "label": "ArciumSignerAccount", "file_type": "code", "source_file": "arcium-psi/programs/arcium-psi/src/lib.rs", "source_location": "L199"}, {"id": "computationdefinitionaccount", "label": "ComputationDefinitionAccount", "file_type": "code", "source_file": "arcium-psi/programs/arcium-psi/src/lib.rs", "source_location": "L209"}, {"id": "cluster", "label": "Cluster", "file_type": "code", "source_file": "arcium-psi/programs/arcium-psi/src/lib.rs", "source_location": "L211"}, {"id": "feepool", "label": "FeePool", "file_type": "code", "source_file": "arcium-psi/programs/arcium-psi/src/lib.rs", "source_location": "L213"}, {"id": "clockaccount", "label": "ClockAccount", "file_type": "code", "source_file": "arcium-psi/programs/arcium-psi/src/lib.rs", "source_location": "L215"}, {"id": "src_lib_psiintersectcallback", "label": "PsiIntersectCallback", "file_type": "code", "source_file": "arcium-psi/programs/arcium-psi/src/lib.rs", "source_location": "L224"}, {"id": "src_lib_userstate", "label": "UserState", "file_type": "code", "source_file": "arcium-psi/programs/arcium-psi/src/lib.rs", "source_location": "L239"}, {"id": "pubkey", "label": "Pubkey", "file_type": "code", "source_file": "arcium-psi/programs/arcium-psi/src/lib.rs", "source_location": "L240"}, {"id": "src_lib_psierror", "label": "PsiError", "file_type": "code", "source_file": "arcium-psi/programs/arcium-psi/src/lib.rs", "source_location": "L251"}, {"id": "src_lib_offchaincircuitsource", "label": "OffChainCircuitSource", "file_type": "code", "source_file": "arcium-psi/programs/arcium-psi/src/lib.rs", "source_location": "L263"}, {"id": "string", "label": "String", "file_type": "code", "source_file": "arcium-psi/programs/arcium-psi/src/lib.rs", "source_location": "L265"}, {"id": "src_lib_psiquery", "label": "PsiQuery", "file_type": "code", "source_file": "arcium-psi/programs/arcium-psi/src/lib.rs", "source_location": "L274"}, {"id": "src_lib_psiresult", "label": "PsiResult", "file_type": "code", "source_file": "arcium-psi/programs/arcium-psi/src/lib.rs", "source_location": "L286"}, {"id": "src_lib_off_chain_circuit_source_round_trip", "label": "off_chain_circuit_source_round_trip()", "file_type": "code", "source_file": "arcium-psi/programs/arcium-psi/src/lib.rs", "source_location": "L300"}, {"id": "src_lib_psi_query_round_trip", "label": "psi_query_round_trip()", "file_type": "code", "source_file": "arcium-psi/programs/arcium-psi/src/lib.rs", "source_location": "L315"}, {"id": "src_lib_psi_result_round_trip", "label": "psi_result_round_trip()", "file_type": "code", "source_file": "arcium-psi/programs/arcium-psi/src/lib.rs", "source_location": "L332"}], "edges": [{"source": "home_user_arcium_messenger_arcium_psi_programs_arcium_psi_src_lib_rs", "target": "prelude", "relation": "imports_from", "confidence": "EXTRACTED", "source_file": "arcium-psi/programs/arcium-psi/src/lib.rs", "source_location": "L2", "weight": 1.0, "context": "import"}, {"source": "home_user_arcium_messenger_arcium_psi_programs_arcium_psi_src_lib_rs", "target": "prelude", "relation": "imports_from", "confidence": "EXTRACTED", "source_file": "arcium-psi/programs/arcium-psi/src/lib.rs", "source_location": "L3", "weight": 1.0, "context": "import"}, {"source": "home_user_arcium_messenger_arcium_psi_programs_arcium_psi_src_lib_rs", "target": "super", "relation": "imports_from", "confidence": "EXTRACTED", "source_file": "arcium-psi/programs/arcium-psi/src/lib.rs", "source_location": "L9", "weight": 1.0, "context": "import"}, {"source": "home_user_arcium_messenger_arcium_psi_programs_arcium_psi_src_lib_rs", "target": "src_lib_init_user", "relation": "contains", "confidence": "EXTRACTED", "source_file": "arcium-psi/programs/arcium-psi/src/lib.rs", "source_location": "L11", "weight": 1.0}, {"source": "src_lib_init_user", "target": "context", "relation": "references", "confidence": "EXTRACTED", "source_file": "arcium-psi/programs/arcium-psi/src/lib.rs", "source_location": "L11", "weight": 1.0, "context": "parameter_type"}, {"source": "src_lib_init_user", "target": "inituser", "relation": "references", "confidence": "EXTRACTED", "source_file": "arcium-psi/programs/arcium-psi/src/lib.rs", "source_location": "L11", "weight": 1.0, "context": "generic_arg"}, {"source": "src_lib_init_user", "target": "result", "relation": "references", "confidence": "EXTRACTED", "source_file": "arcium-psi/programs/arcium-psi/src/lib.rs", "source_location": "L11", "weight": 1.0, "context": "return_type"}, {"source": "home_user_arcium_messenger_arcium_psi_programs_arcium_psi_src_lib_rs", "target": "src_lib_submit_query", "relation": "contains", "confidence": "EXTRACTED", "source_file": "arcium-psi/programs/arcium-psi/src/lib.rs", "source_location": "L19", "weight": 1.0}, {"source": "src_lib_submit_query", "target": "context", "relation": "references", "confidence": "EXTRACTED", "source_file": "arcium-psi/programs/arcium-psi/src/lib.rs", "source_location": "L19", "weight": 1.0, "context": "parameter_type"}, {"source": "src_lib_submit_query", "target": "submitquery", "relation": "references", "confidence": "EXTRACTED", "source_file": "arcium-psi/programs/arcium-psi/src/lib.rs", "source_location": "L19", "weight": 1.0, "context": "generic_arg"}, {"source": "src_lib_submit_query", "target": "vec", "relation": "references", "confidence": "EXTRACTED", "source_file": "arcium-psi/programs/arcium-psi/src/lib.rs", "source_location": "L19", "weight": 1.0, "context": "parameter_type"}, {"source": "src_lib_submit_query", "target": "result", "relation": "references", "confidence": "EXTRACTED", "source_file": "arcium-psi/programs/arcium-psi/src/lib.rs", "source_location": "L19", "weight": 1.0, "context": "return_type"}, {"source": "home_user_arcium_messenger_arcium_psi_programs_arcium_psi_src_lib_rs", "target": "src_lib_init_psi_intersect_comp_def", "relation": "contains", "confidence": "EXTRACTED", "source_file": "arcium-psi/programs/arcium-psi/src/lib.rs", "source_location": "L37", "weight": 1.0}, {"source": "src_lib_init_psi_intersect_comp_def", "target": "context", "relation": "references", "confidence": "EXTRACTED", "source_file": "arcium-psi/programs/arcium-psi/src/lib.rs", "source_location": "L37", "weight": 1.0, "context": "parameter_type"}, {"source": "src_lib_init_psi_intersect_comp_def", "target": "initpsiintersectcompdef", "relation": "references", "confidence": "EXTRACTED", "source_file": "arcium-psi/programs/arcium-psi/src/lib.rs", "source_location": "L37", "weight": 1.0, "context": "generic_arg"}, {"source": "src_lib_init_psi_intersect_comp_def", "target": "result", "relation": "references", "confidence": "EXTRACTED", "source_file": "arcium-psi/programs/arcium-psi/src/lib.rs", "source_location": "L37", "weight": 1.0, "context": "return_type"}, {"source": "home_user_arcium_messenger_arcium_psi_programs_arcium_psi_src_lib_rs", "target": "src_lib_submit_psi_query", "relation": "contains", "confidence": "EXTRACTED", "source_file": "arcium-psi/programs/arcium-psi/src/lib.rs", "source_location": "L52", "weight": 1.0}, {"source": "src_lib_submit_psi_query", "target": "context", "relation": "references", "confidence": "EXTRACTED", "source_file": "arcium-psi/programs/arcium-psi/src/lib.rs", "source_location": "L52", "weight": 1.0, "context": "parameter_type"}, {"source": "src_lib_submit_psi_query", "target": "submitpsiquery", "relation": "references", "confidence": "EXTRACTED", "source_file": "arcium-psi/programs/arcium-psi/src/lib.rs", "source_location": "L52", "weight": 1.0, "context": "generic_arg"}, {"source": "src_lib_submit_psi_query", "target": "sharedencryptedstruct", "relation": "references", "confidence": "EXTRACTED", "source_file": "arcium-psi/programs/arcium-psi/src/lib.rs", "source_location": "L52", "weight": 1.0, "context": "parameter_type"}, {"source": "src_lib_submit_psi_query", "target": "sharedencryptedstruct", "relation": "references", "confidence": "EXTRACTED", "source_file": "arcium-psi/programs/arcium-psi/src/lib.rs", "source_location": "L52", "weight": 1.0, "context": "parameter_type"}, {"source": "src_lib_submit_psi_query", "target": "result", "relation": "references", "confidence": "EXTRACTED", "source_file": "arcium-psi/programs/arcium-psi/src/lib.rs", "source_location": "L52", "weight": 1.0, "context": "return_type"}, {"source": "home_user_arcium_messenger_arcium_psi_programs_arcium_psi_src_lib_rs", "target": "src_lib_psi_intersect_callback", "relation": "contains", "confidence": "EXTRACTED", "source_file": "arcium-psi/programs/arcium-psi/src/lib.rs", "source_location": "L123", "weight": 1.0}, {"source": "src_lib_psi_intersect_callback", "target": "context", "relation": "references", "confidence": "EXTRACTED", "source_file": "arcium-psi/programs/arcium-psi/src/lib.rs", "source_location": "L123", "weight": 1.0, "context": "parameter_type"}, {"source": "src_lib_psi_intersect_callback", "target": "psiintersectcallback", "relation": "references", "confidence": "EXTRACTED", "source_file": "arcium-psi/programs/arcium-psi/src/lib.rs", "source_location": "L123", "weight": 1.0, "context": "generic_arg"}, {"source": "src_lib_psi_intersect_callback", "target": "signedcomputationoutputs", "relation": "references", "confidence": "EXTRACTED", "source_file": "arcium-psi/programs/arcium-psi/src/lib.rs", "source_location": "L123", "weight": 1.0, "context": "parameter_type"}, {"source": "src_lib_psi_intersect_callback", "target": "psiintersectoutput", "relation": "references", "confidence": "EXTRACTED", "source_file": "arcium-psi/programs/arcium-psi/src/lib.rs", "source_location": "L123", "weight": 1.0, "context": "generic_arg"}, {"source": "src_lib_psi_intersect_callback", "target": "result", "relation": "references", "confidence": "EXTRACTED", "source_file": "arcium-psi/programs/arcium-psi/src/lib.rs", "source_location": "L123", "weight": 1.0, "context": "return_type"}, {"source": "home_user_arcium_messenger_arcium_psi_programs_arcium_psi_src_lib_rs", "target": "src_lib_inituser", "relation": "contains", "confidence": "EXTRACTED", "source_file": "arcium-psi/programs/arcium-psi/src/lib.rs", "source_location": "L148", "weight": 1.0}, {"source": "src_lib_inituser", "target": "account", "relation": "references", "confidence": "EXTRACTED", "source_file": "arcium-psi/programs/arcium-psi/src/lib.rs", "source_location": "L155", "weight": 1.0, "context": "field"}, {"source": "src_lib_inituser", "target": "userstate", "relation": "references", "confidence": "EXTRACTED", "source_file": "arcium-psi/programs/arcium-psi/src/lib.rs", "source_location": "L155", "weight": 1.0, "context": "generic_arg"}, {"source": "src_lib_inituser", "target": "signer", "relation": "references", "confidence": "EXTRACTED", "source_file": "arcium-psi/programs/arcium-psi/src/lib.rs", "source_location": "L157", "weight": 1.0, "context": "field"}, {"source": "src_lib_inituser", "target": "program", "relation": "references", "confidence": "EXTRACTED", "source_file": "arcium-psi/programs/arcium-psi/src/lib.rs", "source_location": "L158", "weight": 1.0, "context": "field"}, {"source": "src_lib_inituser", "target": "system", "relation": "references", "confidence": "EXTRACTED", "source_file": "arcium-psi/programs/arcium-psi/src/lib.rs", "source_location": "L158", "weight": 1.0, "context": "generic_arg"}, {"source": "home_user_arcium_messenger_arcium_psi_programs_arcium_psi_src_lib_rs", "target": "src_lib_submitquery", "relation": "contains", "confidence": "EXTRACTED", "source_file": "arcium-psi/programs/arcium-psi/src/lib.rs", "source_location": "L162", "weight": 1.0}, {"source": "src_lib_submitquery", "target": "account", "relation": "references", "confidence": "EXTRACTED", "source_file": "arcium-psi/programs/arcium-psi/src/lib.rs", "source_location": "L164", "weight": 1.0, "context": "field"}, {"source": "src_lib_submitquery", "target": "userstate", "relation": "references", "confidence": "EXTRACTED", "source_file": "arcium-psi/programs/arcium-psi/src/lib.rs", "source_location": "L164", "weight": 1.0, "context": "generic_arg"}, {"source": "src_lib_submitquery", "target": "signer", "relation": "references", "confidence": "EXTRACTED", "source_file": "arcium-psi/programs/arcium-psi/src/lib.rs", "source_location": "L165", "weight": 1.0, "context": "field"}, {"source": "home_user_arcium_messenger_arcium_psi_programs_arcium_psi_src_lib_rs", "target": "src_lib_initpsiintersectcompdef", "relation": "contains", "confidence": "EXTRACTED", "source_file": "arcium-psi/programs/arcium-psi/src/lib.rs", "source_location": "L174", "weight": 1.0}, {"source": "src_lib_initpsiintersectcompdef", "target": "signer", "relation": "references", "confidence": "EXTRACTED", "source_file": "arcium-psi/programs/arcium-psi/src/lib.rs", "source_location": "L176", "weight": 1.0, "context": "field"}, {"source": "src_lib_initpsiintersectcompdef", "target": "account", "relation": "references", "confidence": "EXTRACTED", "source_file": "arcium-psi/programs/arcium-psi/src/lib.rs", "source_location": "L178", "weight": 1.0, "context": "field"}, {"source": "src_lib_initpsiintersectcompdef", "target": "mxeaccount", "relation": "references", "confidence": "EXTRACTED", "source_file": "arcium-psi/programs/arcium-psi/src/lib.rs", "source_location": "L178", "weight": 1.0, "context": "generic_arg"}, {"source": "src_lib_initpsiintersectcompdef", "target": "uncheckedaccount", "relation": "references", "confidence": "EXTRACTED", "source_file": "arcium-psi/programs/arcium-psi/src/lib.rs", "source_location": "L181", "weight": 1.0, "context": "field"}, {"source": "src_lib_initpsiintersectcompdef", "target": "uncheckedaccount", "relation": "references", "confidence": "EXTRACTED", "source_file": "arcium-psi/programs/arcium-psi/src/lib.rs", "source_location": "L184", "weight": 1.0, "context": "field"}, {"source": "src_lib_initpsiintersectcompdef", "target": "uncheckedaccount", "relation": "references", "confidence": "EXTRACTED", "source_file": "arcium-psi/programs/arcium-psi/src/lib.rs", "source_location": "L186", "weight": 1.0, "context": "field"}, {"source": "src_lib_initpsiintersectcompdef", "target": "program", "relation": "references", "confidence": "EXTRACTED", "source_file": "arcium-psi/programs/arcium-psi/src/lib.rs", "source_location": "L187", "weight": 1.0, "context": "field"}, {"source": "src_lib_initpsiintersectcompdef", "target": "system", "relation": "references", "confidence": "EXTRACTED", "source_file": "arcium-psi/programs/arcium-psi/src/lib.rs", "source_location": "L187", "weight": 1.0, "context": "generic_arg"}, {"source": "src_lib_initpsiintersectcompdef", "target": "program", "relation": "references", "confidence": "EXTRACTED", "source_file": "arcium-psi/programs/arcium-psi/src/lib.rs", "source_location": "L188", "weight": 1.0, "context": "field"}, {"source": "src_lib_initpsiintersectcompdef", "target": "arcium", "relation": "references", "confidence": "EXTRACTED", "source_file": "arcium-psi/programs/arcium-psi/src/lib.rs", "source_location": "L188", "weight": 1.0, "context": "generic_arg"}, {"source": "home_user_arcium_messenger_arcium_psi_programs_arcium_psi_src_lib_rs", "target": "src_lib_submitpsiquery", "relation": "contains", "confidence": "EXTRACTED", "source_file": "arcium-psi/programs/arcium-psi/src/lib.rs", "source_location": "L194", "weight": 1.0}, {"source": "src_lib_submitpsiquery", "target": "signer", "relation": "references", "confidence": "EXTRACTED", "source_file": "arcium-psi/programs/arcium-psi/src/lib.rs", "source_location": "L196", "weight": 1.0, "context": "field"}, {"source": "src_lib_submitpsiquery", "target": "account", "relation": "references", "confidence": "EXTRACTED", "source_file": "arcium-psi/programs/arcium-psi/src/lib.rs", "source_location": "L197", "weight": 1.0, "context": "field"}, {"source": "src_lib_submitpsiquery", "target": "mxeaccount", "relation": "references", "confidence": "EXTRACTED", "source_file": "arcium-psi/programs/arcium-psi/src/lib.rs", "source_location": "L197", "weight": 1.0, "context": "generic_arg"}, {"source": "src_lib_submitpsiquery", "target": "account", "relation": "references", "confidence": "EXTRACTED", "source_file": "arcium-psi/programs/arcium-psi/src/lib.rs", "source_location": "L199", "weight": 1.0, "context": "field"}, {"source": "src_lib_submitpsiquery", "target": "arciumsigneraccount", "relation": "references", "confidence": "EXTRACTED", "source_file": "arcium-psi/programs/arcium-psi/src/lib.rs", "source_location": "L199", "weight": 1.0, "context": "generic_arg"}, {"source": "src_lib_submitpsiquery", "target": "uncheckedaccount", "relation": "references", "confidence": "EXTRACTED", "source_file": "arcium-psi/programs/arcium-psi/src/lib.rs", "source_location": "L202", "weight": 1.0, "context": "field"}, {"source": "src_lib_submitpsiquery", "target": "uncheckedaccount", "relation": "references", "confidence": "EXTRACTED", "source_file": "arcium-psi/programs/arcium-psi/src/lib.rs", "source_location": "L205", "weight": 1.0, "context": "field"}, {"source": "src_lib_submitpsiquery", "target": "uncheckedaccount", "relation": "references", "confidence": "EXTRACTED", "source_file": "arcium-psi/programs/arcium-psi/src/lib.rs", "source_location": "L208", "weight": 1.0, "context": "field"}, {"source": "src_lib_submitpsiquery", "target": "account", "relation": "references", "confidence": "EXTRACTED", "source_file": "arcium-psi/programs/arcium-psi/src/lib.rs", "source_location": "L209", "weight": 1.0, "context": "field"}, {"source": "src_lib_submitpsiquery", "target": "computationdefinitionaccount", "relation": "references", "confidence": "EXTRACTED", "source_file": "arcium-psi/programs/arcium-psi/src/lib.rs", "source_location": "L209", "weight": 1.0, "context": "generic_arg"}, {"source": "src_lib_submitpsiquery", "target": "account", "relation": "references", "confidence": "EXTRACTED", "source_file": "arcium-psi/programs/arcium-psi/src/lib.rs", "source_location": "L211", "weight": 1.0, "context": "field"}, {"source": "src_lib_submitpsiquery", "target": "cluster", "relation": "references", "confidence": "EXTRACTED", "source_file": "arcium-psi/programs/arcium-psi/src/lib.rs", "source_location": "L211", "weight": 1.0, "context": "generic_arg"}, {"source": "src_lib_submitpsiquery", "target": "account", "relation": "references", "confidence": "EXTRACTED", "source_file": "arcium-psi/programs/arcium-psi/src/lib.rs", "source_location": "L213", "weight": 1.0, "context": "field"}, {"source": "src_lib_submitpsiquery", "target": "feepool", "relation": "references", "confidence": "EXTRACTED", "source_file": "arcium-psi/programs/arcium-psi/src/lib.rs", "source_location": "L213", "weight": 1.0, "context": "generic_arg"}, {"source": "src_lib_submitpsiquery", "target": "account", "relation": "references", "confidence": "EXTRACTED", "source_file": "arcium-psi/programs/arcium-psi/src/lib.rs", "source_location": "L215", "weight": 1.0, "context": "field"}, {"source": "src_lib_submitpsiquery", "target": "clockaccount", "relation": "references", "confidence": "EXTRACTED", "source_file": "arcium-psi/programs/arcium-psi/src/lib.rs", "source_location": "L215", "weight": 1.0, "context": "generic_arg"}, {"source": "src_lib_submitpsiquery", "target": "program", "relation": "references", "confidence": "EXTRACTED", "source_file": "arcium-psi/programs/arcium-psi/src/lib.rs", "source_location": "L216", "weight": 1.0, "context": "field"}, {"source": "src_lib_submitpsiquery", "target": "system", "relation": "references", "confidence": "EXTRACTED", "source_file": "arcium-psi/programs/arcium-psi/src/lib.rs", "source_location": "L216", "weight": 1.0, "context": "generic_arg"}, {"source": "src_lib_submitpsiquery", "target": "program", "relation": "references", "confidence": "EXTRACTED", "source_file": "arcium-psi/programs/arcium-psi/src/lib.rs", "source_location": "L217", "weight": 1.0, "context": "field"}, {"source": "src_lib_submitpsiquery", "target": "arcium", "relation": "references", "confidence": "EXTRACTED", "source_file": "arcium-psi/programs/arcium-psi/src/lib.rs", "source_location": "L217", "weight": 1.0, "context": "generic_arg"}, {"source": "home_user_arcium_messenger_arcium_psi_programs_arcium_psi_src_lib_rs", "target": "src_lib_psiintersectcallback", "relation": "contains", "confidence": "EXTRACTED", "source_file": "arcium-psi/programs/arcium-psi/src/lib.rs", "source_location": "L224", "weight": 1.0}, {"source": "src_lib_psiintersectcallback", "target": "program", "relation": "references", "confidence": "EXTRACTED", "source_file": "arcium-psi/programs/arcium-psi/src/lib.rs", "source_location": "L225", "weight": 1.0, "context": "field"}, {"source": "src_lib_psiintersectcallback", "target": "arcium", "relation": "references", "confidence": "EXTRACTED", "source_file": "arcium-psi/programs/arcium-psi/src/lib.rs", "source_location": "L225", "weight": 1.0, "context": "generic_arg"}, {"source": "src_lib_psiintersectcallback", "target": "account", "relation": "references", "confidence": "EXTRACTED", "source_file": "arcium-psi/programs/arcium-psi/src/lib.rs", "source_location": "L226", "weight": 1.0, "context": "field"}, {"source": "src_lib_psiintersectcallback", "target": "computationdefinitionaccount", "relation": "references", "confidence": "EXTRACTED", "source_file": "arcium-psi/programs/arcium-psi/src/lib.rs", "source_location": "L226", "weight": 1.0, "context": "generic_arg"}, {"source": "src_lib_psiintersectcallback", "target": "account", "relation": "references", "confidence": "EXTRACTED", "source_file": "arcium-psi/programs/arcium-psi/src/lib.rs", "source_location": "L227", "weight": 1.0, "context": "field"}, {"source": "src_lib_psiintersectcallback", "target": "mxeaccount", "relation": "references", "confidence": "EXTRACTED", "source_file": "arcium-psi/programs/arcium-psi/src/lib.rs", "source_location": "L227", "weight": 1.0, "context": "generic_arg"}, {"source": "src_lib_psiintersectcallback", "target": "uncheckedaccount", "relation": "references", "confidence": "EXTRACTED", "source_file": "arcium-psi/programs/arcium-psi/src/lib.rs", "source_location": "L229", "weight": 1.0, "context": "field"}, {"source": "src_lib_psiintersectcallback", "target": "account", "relation": "references", "confidence": "EXTRACTED", "source_file": "arcium-psi/programs/arcium-psi/src/lib.rs", "source_location": "L230", "weight": 1.0, "context": "field"}, {"source": "src_lib_psiintersectcallback", "target": "cluster", "relation": "references", "confidence": "EXTRACTED", "source_file": "arcium-psi/programs/arcium-psi/src/lib.rs", "source_location": "L230", "weight": 1.0, "context": "generic_arg"}, {"source": "src_lib_psiintersectcallback", "target": "uncheckedaccount", "relation": "references", "confidence": "EXTRACTED", "source_file": "arcium-psi/programs/arcium-psi/src/lib.rs", "source_location": "L233", "weight": 1.0, "context": "field"}, {"source": "home_user_arcium_messenger_arcium_psi_programs_arcium_psi_src_lib_rs", "target": "src_lib_userstate", "relation": "contains", "confidence": "EXTRACTED", "source_file": "arcium-psi/programs/arcium-psi/src/lib.rs", "source_location": "L239", "weight": 1.0}, {"source": "src_lib_userstate", "target": "pubkey", "relation": "references", "confidence": "EXTRACTED", "source_file": "arcium-psi/programs/arcium-psi/src/lib.rs", "source_location": "L240", "weight": 1.0, "context": "field"}, {"source": "home_user_arcium_messenger_arcium_psi_programs_arcium_psi_src_lib_rs", "target": "src_lib_psierror", "relation": "contains", "confidence": "EXTRACTED", "source_file": "arcium-psi/programs/arcium-psi/src/lib.rs", "source_location": "L251", "weight": 1.0}, {"source": "home_user_arcium_messenger_arcium_psi_programs_arcium_psi_src_lib_rs", "target": "src_lib_offchaincircuitsource", "relation": "contains", "confidence": "EXTRACTED", "source_file": "arcium-psi/programs/arcium-psi/src/lib.rs", "source_location": "L263", "weight": 1.0}, {"source": "src_lib_offchaincircuitsource", "target": "string", "relation": "references", "confidence": "EXTRACTED", "source_file": "arcium-psi/programs/arcium-psi/src/lib.rs", "source_location": "L265", "weight": 1.0, "context": "field"}, {"source": "home_user_arcium_messenger_arcium_psi_programs_arcium_psi_src_lib_rs", "target": "src_lib_psiquery", "relation": "contains", "confidence": "EXTRACTED", "source_file": "arcium-psi/programs/arcium-psi/src/lib.rs", "source_location": "L274", "weight": 1.0}, {"source": "src_lib_psiquery", "target": "vec", "relation": "references", "confidence": "EXTRACTED", "source_file": "arcium-psi/programs/arcium-psi/src/lib.rs", "source_location": "L278", "weight": 1.0, "context": "field"}, {"source": "home_user_arcium_messenger_arcium_psi_programs_arcium_psi_src_lib_rs", "target": "src_lib_psiresult", "relation": "contains", "confidence": "EXTRACTED", "source_file": "arcium-psi/programs/arcium-psi/src/lib.rs", "source_location": "L286", "weight": 1.0}, {"source": "src_lib_psiresult", "target": "vec", "relation": "references", "confidence": "EXTRACTED", "source_file": "arcium-psi/programs/arcium-psi/src/lib.rs", "source_location": "L289", "weight": 1.0, "context": "field"}, {"source": "home_user_arcium_messenger_arcium_psi_programs_arcium_psi_src_lib_rs", "target": "super", "relation": "imports_from", "confidence": "EXTRACTED", "source_file": "arcium-psi/programs/arcium-psi/src/lib.rs", "source_location": "L296", "weight": 1.0, "context": "import"}, {"source": "home_user_arcium_messenger_arcium_psi_programs_arcium_psi_src_lib_rs", "target": "anchor_lang", "relation": "imports_from", "confidence": "EXTRACTED", "source_file": "arcium-psi/programs/arcium-psi/src/lib.rs", "source_location": "L297", "weight": 1.0, "context": "import"}, {"source": "home_user_arcium_messenger_arcium_psi_programs_arcium_psi_src_lib_rs", "target": "src_lib_off_chain_circuit_source_round_trip", "relation": "contains", "confidence": "EXTRACTED", "source_file": "arcium-psi/programs/arcium-psi/src/lib.rs", "source_location": "L300", "weight": 1.0}, {"source": "home_user_arcium_messenger_arcium_psi_programs_arcium_psi_src_lib_rs", "target": "src_lib_psi_query_round_trip", "relation": "contains", "confidence": "EXTRACTED", "source_file": "arcium-psi/programs/arcium-psi/src/lib.rs", "source_location": "L315", "weight": 1.0}, {"source": "home_user_arcium_messenger_arcium_psi_programs_arcium_psi_src_lib_rs", "target": "src_lib_psi_result_round_trip", "relation": "contains", "confidence": "EXTRACTED", "source_file": "arcium-psi/programs/arcium-psi/src/lib.rs", "source_location": "L332", "weight": 1.0}], "raw_calls": [{"caller_nid": "src_lib_init_user", "callee": "key", "is_member_call": true, "source_file": "/home/user/Arcium-messenger-/arcium-psi/programs/arcium-psi/src/lib.rs", "source_location": "L13"}, {"caller_nid": "src_lib_submit_query", "callee": "saturating_add", "is_member_call": true, "source_file": "/home/user/Arcium-messenger-/arcium-psi/programs/arcium-psi/src/lib.rs", "source_location": "L27"}, {"caller_nid": "src_lib_init_psi_intersect_comp_def", "callee": "init_computation_def", "is_member_call": false, "source_file": "/home/user/Arcium-messenger-/arcium-psi/programs/arcium-psi/src/lib.rs", "source_location": "L40"}, {"caller_nid": "src_lib_submit_psi_query", "callee": "encrypted_u64", "is_member_call": true, "source_file": "/home/user/Arcium-messenger-/arcium-psi/programs/arcium-psi/src/lib.rs", "source_location": "L71"}, {"caller_nid": "src_lib_submit_psi_query", "callee": "encrypted_u64", "is_member_call": true, "source_file": "/home/user/Arcium-messenger-/arcium-psi/programs/arcium-psi/src/lib.rs", "source_location": "L71"}, {"caller_nid": "src_lib_submit_psi_query", "callee": "encrypted_u64", "is_member_call": true, "source_file": "/home/user/Arcium-messenger-/arcium-psi/programs/arcium-psi/src/lib.rs", "source_location": "L71"}, {"caller_nid": "src_lib_submit_psi_query", "callee": "encrypted_u64", "is_member_call": true, "source_file": "/home/user/Arcium-messenger-/arcium-psi/programs/arcium-psi/src/lib.rs", "source_location": "L71"}, {"caller_nid": "src_lib_submit_psi_query", "callee": "encrypted_u64", "is_member_call": true, "source_file": "/home/user/Arcium-messenger-/arcium-psi/programs/arcium-psi/src/lib.rs", "source_location": "L71"}, {"caller_nid": "src_lib_submit_psi_query", "callee": "encrypted_u64", "is_member_call": true, "source_file": "/home/user/Arcium-messenger-/arcium-psi/programs/arcium-psi/src/lib.rs", "source_location": "L71"}, {"caller_nid": "src_lib_submit_psi_query", "callee": "encrypted_u64", "is_member_call": true, "source_file": "/home/user/Arcium-messenger-/arcium-psi/programs/arcium-psi/src/lib.rs", "source_location": "L71"}, {"caller_nid": "src_lib_submit_psi_query", "callee": "encrypted_u64", "is_member_call": true, "source_file": "/home/user/Arcium-messenger-/arcium-psi/programs/arcium-psi/src/lib.rs", "source_location": "L71"}, {"caller_nid": "src_lib_submit_psi_query", "callee": "encrypted_u64", "is_member_call": true, "source_file": "/home/user/Arcium-messenger-/arcium-psi/programs/arcium-psi/src/lib.rs", "source_location": "L71"}, {"caller_nid": "src_lib_submit_psi_query", "callee": "encrypted_u64", "is_member_call": true, "source_file": "/home/user/Arcium-messenger-/arcium-psi/programs/arcium-psi/src/lib.rs", "source_location": "L71"}, {"caller_nid": "src_lib_submit_psi_query", "callee": "plaintext_u128", "is_member_call": true, "source_file": "/home/user/Arcium-messenger-/arcium-psi/programs/arcium-psi/src/lib.rs", "source_location": "L71"}, {"caller_nid": "src_lib_submit_psi_query", "callee": "x25519_pubkey", "is_member_call": true, "source_file": "/home/user/Arcium-messenger-/arcium-psi/programs/arcium-psi/src/lib.rs", "source_location": "L71"}, {"caller_nid": "src_lib_submit_psi_query", "callee": "encrypted_u64", "is_member_call": true, "source_file": "/home/user/Arcium-messenger-/arcium-psi/programs/arcium-psi/src/lib.rs", "source_location": "L71"}, {"caller_nid": "src_lib_submit_psi_query", "callee": "encrypted_u64", "is_member_call": true, "source_file": "/home/user/Arcium-messenger-/arcium-psi/programs/arcium-psi/src/lib.rs", "source_location": "L71"}, {"caller_nid": "src_lib_submit_psi_query", "callee": "encrypted_u64", "is_member_call": true, "source_file": "/home/user/Arcium-messenger-/arcium-psi/programs/arcium-psi/src/lib.rs", "source_location": "L71"}, {"caller_nid": "src_lib_submit_psi_query", "callee": "encrypted_u64", "is_member_call": true, "source_file": "/home/user/Arcium-messenger-/arcium-psi/programs/arcium-psi/src/lib.rs", "source_location": "L71"}, {"caller_nid": "src_lib_submit_psi_query", "callee": "encrypted_u64", "is_member_call": true, "source_file": "/home/user/Arcium-messenger-/arcium-psi/programs/arcium-psi/src/lib.rs", "source_location": "L71"}, {"caller_nid": "src_lib_submit_psi_query", "callee": "encrypted_u64", "is_member_call": true, "source_file": "/home/user/Arcium-messenger-/arcium-psi/programs/arcium-psi/src/lib.rs", "source_location": "L71"}, {"caller_nid": "src_lib_submit_psi_query", "callee": "encrypted_u64", "is_member_call": true, "source_file": "/home/user/Arcium-messenger-/arcium-psi/programs/arcium-psi/src/lib.rs", "source_location": "L71"}, {"caller_nid": "src_lib_submit_psi_query", "callee": "encrypted_u64", "is_member_call": true, "source_file": "/home/user/Arcium-messenger-/arcium-psi/programs/arcium-psi/src/lib.rs", "source_location": "L71"}, {"caller_nid": "src_lib_submit_psi_query", "callee": "encrypted_u64", "is_member_call": true, "source_file": "/home/user/Arcium-messenger-/arcium-psi/programs/arcium-psi/src/lib.rs", "source_location": "L71"}, {"caller_nid": "src_lib_submit_psi_query", "callee": "encrypted_u64", "is_member_call": true, "source_file": "/home/user/Arcium-messenger-/arcium-psi/programs/arcium-psi/src/lib.rs", "source_location": "L71"}, {"caller_nid": "src_lib_submit_psi_query", "callee": "plaintext_u128", "is_member_call": true, "source_file": "/home/user/Arcium-messenger-/arcium-psi/programs/arcium-psi/src/lib.rs", "source_location": "L71"}, {"caller_nid": "src_lib_submit_psi_query", "callee": "x25519_pubkey", "is_member_call": true, "source_file": "/home/user/Arcium-messenger-/arcium-psi/programs/arcium-psi/src/lib.rs", "source_location": "L71"}, {"caller_nid": "src_lib_submit_psi_query", "callee": "queue_computation", "is_member_call": false, "source_file": "/home/user/Arcium-messenger-/arcium-psi/programs/arcium-psi/src/lib.rs", "source_location": "L106"}, {"caller_nid": "src_lib_psi_intersect_callback", "callee": "verify_output", "is_member_call": true, "source_file": "/home/user/Arcium-messenger-/arcium-psi/programs/arcium-psi/src/lib.rs", "source_location": "L129"}, {"caller_nid": "src_lib_off_chain_circuit_source_round_trip", "callee": "serialize", "is_member_call": true, "source_file": "/home/user/Arcium-messenger-/arcium-psi/programs/arcium-psi/src/lib.rs", "source_location": "L307"}, {"caller_nid": "src_lib_psi_query_round_trip", "callee": "serialize", "is_member_call": true, "source_file": "/home/user/Arcium-messenger-/arcium-psi/programs/arcium-psi/src/lib.rs", "source_location": "L323"}, {"caller_nid": "src_lib_psi_result_round_trip", "callee": "serialize", "is_member_call": true, "source_file": "/home/user/Arcium-messenger-/arcium-psi/programs/arcium-psi/src/lib.rs", "source_location": "L339"}]}